Workbook

Sheet 0_README
A1: DAY 28 — MONETIZATION MODEL
A2: AI Pricing · GTM · Evidence — AI-IN-ACTION Track 1
A4: QUY ƯỚC MÀU — CHỈ ĐIỀN VÀO Ô MÀU VÀNG
A5: Ô VÀNG, chữ xanh dương | B5: Ô bạn phải điền
A6: Ô XÁM, chữ đen | B6: Công thức tự tính — KHÔNG SỬA
A7: Chữ xanh lá | B7: Link sang tab khác
A8: Ô XÁM đậm nhạt | B8: Bảng tham chiếu, chỉ đọc
A10: THỨ TỰ LÀM — 6 TRẠM, 120 PHÚT
A11: Trạm 1 · 15' | B11: Ngân sách khách & định nghĩa Job → điền S1–S2 của tab 1_Cost_Job
A12: Trạm 2 · 20' | B12: Value Metric → tab 3_Value_Metric
A13: Trạm 3 · 30' | B13: Cost/Job, giá sàn & giá trần → tab 1_Cost_Job (S3–S8) rồi 2_Pricing
A14: Trạm 4 · 20' | B14: Kênh phân phối & Affordability Test → tab 4_Channel_Fit
A15: Trạm 5 · 15' | B15: Pain Moment & 90-Day Plan → tab 5_90Day_Plan
A16: Trạm 6 · 20' | B16: Evidence Pack & ráp One-Pager → tab 5_90Day_Plan + file .docx
A18: 3 QUY TẮC KHÔNG ĐƯỢC PHÁ
A19: 1. Chia cho số job HOÀN THÀNH, không phải số job đã thử.
A20: 2. HITL và Retry không được để 0 nếu không có lý do viết ra được.
A21: 3. Mọi con số giá API phải có NGÀY kiểm tra (xem tab 6_Benchmarks).
A23: Giá tham chiếu trong workbook này được chốt ngày 26/08/2026. Nhiều mức giá là KHUYẾN MẠI CÓ HẠN.
A24: Bạn PHẢI tự mở lại trang giá của nhà cung cấp và cập nhật — đây là một phần của bài tập.

Sheet 1_Cost_Job
A1: TAB 1 — COST/JOB CALCULATOR
A2: Trạm 1 (S1–S2) và Trạm 3 (S3–S8). Chỉ điền ô vàng.
A4: S1. ĐỊNH NGHĨA JOB
A5: 1 job của bạn là gì? | B5: 1 hồ sơ báo giá & phương án tài chính BĐS hợp lệ được phê duyệt chính thức (kèm snapshot SHA-256, Time-Travel policy và Compliance gate) | D5: Phải là thứ KHÁCH coi là giá trị — không phải '1 request'
A6: Biến thể HITL: A hay B? | B6: B | D6: A = khách tự xử lý ca escalate · B = BẠN chịu (outcome/managed)
A8: S2. KHỐI LƯỢNG
A9: Số job THỬ / tháng | B9: 1000 | C9: job
A10: Containment rate (AI tự làm xong) | B10: 0.82 | D10: Chưa đo → ước tính và ghi rõ
A11: → Số job HOÀN THÀNH / tháng | B11: =B9*B10 -> 820 | C11: job | D11: MẪU SỐ của Cost/Job
A12: → Số job KHÔNG xong / tháng | B12: =B9-B11 -> 180 | C12: job | D12: Số ca phải escalate
A14: S3. API — LLM
A15: Giá input ($ / 1M token) | B15: 1 | D15: Claude Haiku 4.5 — xem tab 6_Benchmarks
A16: Giá output ($ / 1M token) | B16: 5
A17: Giá cache WRITE ($ / 1M token) | B17: 1.25 | D17: Anthropic 5-phút = 1,25× input
A18: Giá cache READ ($ / 1M token) | B18: 0.1 | D18: ≈ 0,1× input (giảm 90%)
A19: Số lượt (turns) / job | B19: 3 | C19: lượt
A20: Token input CACHE ĐƯỢC / lượt | B20: 6000 | C20: token | D20: System prompt + KB + few-shot
A21: Token input FRESH / lượt | B21: 1500 | C21: token | D21: Câu hỏi khách + dữ liệu động
A22: Token output / lượt | B22: 700 | C22: token
A23: → Cache write / job | B23: =B20*B17/1000000 -> 0.0075
A24: → Cache read / job | B24: =(B19-1)*B20*B18/1000000 -> 0.0012
A25: → Input fresh / job | B25: =B19*B21*B15/1000000 -> 0.0045
A26: → Output / job | B26: =B19*B22*B16/1000000 -> 0.0105
A27: → LLM / job — CÓ prompt caching | B27: =SUM(B23:B26) -> 0.0237
A28: → LLM / job — KHÔNG cache | B28: =B19*(B20+B21)*B15/1000000+B26 -> 0.033
A29: → % tiết kiệm nhờ caching | B29: =IF(B28=0,0,1-B27/B28) -> 0.28181818 | D29: Đòn bẩy rẻ nhất bạn có
A30: Dùng Batch API? (1 = có, 0 = không) | B30: 0 | D30: Batch giảm 50% — chỉ khi job KHÔNG cần realtime
A31: → LLM / job sau Batch | B31: =B27*(1-B30*0.5) -> 0.0237
A33: S4. API — SPEECH (để 0 nếu sản phẩm không có thoại)
A34: Giá STT ($ / phút) | B34: 0 | D34: Deepgram streaming list $0,0077/phút
A35: Số phút audio / job | B35: 0 | C35: phút
A36: Giá TTS ($ / 1M ký tự) | B36: 0 | D36: ElevenLabs Flash $50 · Google Standard $4
A37: Số ký tự TTS / job | B37: 0 | C37: ký tự | D37: ≈ 900 ký tự cho mỗi phút bot nói
A38: → Speech / job | B38: =B34*B35+B36*B37/1000000 -> 0
A40: S5. INFRA
A41: Infra / job ($) | B41: 0.02 | D41: Vector DB, embedding, storage, logging
A42: Telephony ($ / phút) | B42: 0
A43: → Infra / job | B43: =B41+B42*B35 -> 0.02
A45: S6. RETRY
A46: Tỷ lệ job phải chạy lại | B46: 0.08 | D46: ĐỪNG để 0%. Thực tế 5–10% là bình thường
A47: → Retry / job | B47: =(B31+B38)*B46 -> 0.001896
A49: S7. HITL — người trong vòng lặp
A50: Chi phí nhân sự ($ / giờ, fully-loaded) | B50: 9 | D50: Gồm lương + bảo hiểm + quản lý + chỗ ngồi
A51: % hội thoại QA nội bộ | B51: 0.05 | D51: Luôn có, kể cả Biến thể A
A52: Số phút QA / ca | B52: 2 | C52: phút
A53: Số phút xử lý 1 ca escalate | B53: 6 | C53: phút
A54: → QA nội bộ / tháng | B54: =B9*B51*(B52/60)*B50 -> 15
A55: → Escalation / tháng (chỉ Biến thể B) | B55: =IF(B6="B",B12*(B53/60)*B50,0) -> 162 | D55: Biến thể A → 0 vì khách tự chịu
A56: → Tổng HITL / tháng | B56: =B54+B55 -> 177
A58: S8. OVERHEAD (tuỳ chọn)
A59: R&D + Sales phân bổ / tháng ($) | B59: 0 | D59: Để 0 nếu chỉ muốn xem Cost/Job thuần COGS
A61: KẾT QUẢ
A62: Chi phí biến đổi / tháng (API + Speech + Infra + Retry) | B62: =B9*(B31+B38+B43+B47) -> 45.596
A63: HITL / tháng | B63: =B56 -> 177
A64: Overhead / tháng | B64: =B59 -> 0
A65: TỔNG CHI PHÍ / tháng | B65: =B62+B63+B64 -> 222.596
A66: ★ COST/JOB (chưa overhead) | B66: =IF(B11=0,0,(B62+B63)/B11) -> 0.27145854 | C66: $/job | D66: Con số chảy sang tab 2_Pricing
A67: ★ COST/JOB (có overhead) | B67: =IF(B11=0,0,B65/B11) -> 0.27145854 | C67: $/job
A68: Tỷ giá (₫ / USD) — giả định | B68: 26000 | C68: ₫/USD | D68: Thay bằng tỷ giá thực tế khi làm bài
A69: → Cost/Job quy đổi | B69: =B66*B68 -> 7057.922 | C69: ₫/job
A71: THÀNH PHẦN NÀO ĂN NHIỀU NHẤT? (kiểm tra nhanh)
A72: LLM | B72: =B9*B31 -> 23.7 | C72: =IF($B$65=0,0,B72/$B$65) -> 0.10647092
A73: Speech | B73: =B9*B38 -> 0 | C73: =IF($B$65=0,0,B73/$B$65) -> 0
A74: Infra | B74: =B9*B43 -> 20 | C74: =IF($B$65=0,0,B74/$B$65) -> 0.089848874
A75: Retry | B75: =B9*B47 -> 1.896 | C75: =IF($B$65=0,0,B75/$B$65) -> 0.0085176733
A76: HITL | B76: =B56 -> 177 | C76: =IF($B$65=0,0,B76/$B$65) -> 0.79516254
A77: Overhead | B77: =B59 -> 0 | C77: =IF($B$65=0,0,B77/$B$65) -> 0
A78: Nếu LLM chiếm >80% thì gần như chắc chắn bạn đang thiếu chi phí ở S5–S7.

Sheet 2_Pricing
A1: TAB 2 — PRICING SANITY CHECK
A2: Trạm 3. Cost/Job tự lấy từ tab 1. Bạn điền giá bán và các con số neo giá.
A4: GIÁ SÀN
A5: Cost/Job (từ tab 1_Cost_Job) | B5: ='1_Cost_Job'!B66 -> 0.27145854 | C5: $/job
A6: Hệ số an toàn tối thiểu | B6: 3 | C6: × | D6: Giá bán ≥ 3 × Cost/Job
A7: → GIÁ SÀN | B7: =B5*B6 -> 0.81437561 | C7: $/job
A9: GIÁ TRẦN — NEO THEO THỨ KHÁCH ĐANG CHI
A10: Giá trị khách tiết kiệm được / tháng ($) | B10: 4000 | D10: Neo theo giá trị
A11: Số job / tháng của 1 khách | B11: 1000 | C11: job
A12: → Trần theo giá trị — mức 10% | B12: =IF(B11=0,0,B10*0.1/B11) -> 0.4 | C12: $/job
A13: → Trần theo giá trị — mức 25% | B13: =IF(B11=0,0,B10*0.25/B11) -> 1 | C13: $/job
A14: Lương / tháng của vị trí bị thay ($) | B14: 1500 | D14: Neo theo nhân công
A15: → Trần theo nhân công — mức 50% | B15: =IF(B11=0,0,B14*0.5/B11) -> 0.75 | C15: $/job
A16: → Trần theo nhân công — mức 70% | B16: =IF(B11=0,0,B14*0.7/B11) -> 1.05 | C16: $/job
A18: GIÁ BÁN CỦA BẠN
A19: ★ Giá bán đề xuất ($ / job) | B19: 0.99 | C19: $/job | D19: Tham chiếu: Intercom Fin $0,99 · Zendesk $1,50
A20: → Bội số so với Cost/Job | B20: =IF(B5=0,0,B19/B5) -> 3.6469658
A21: → GROSS MARGIN | B21: =IF(B19=0,0,(B19-B5)/B19) -> 0.72579946
A22: → Đèn: bội số ≥ 3? | B22: =IF(B20>=B6,"OK — ĐẠT","KHÔNG ĐẠT — quay lại tab 1") -> OK — ĐẠT
A23: → Đèn: Gross Margin | B23: =IF(B21>=0.6,"OK — AN TOÀN (≥60%)",IF(B21>=0.5,"CẢNH BÁO (50–60%)","NGUY HIỂM (<50%)")) -> OK — AN TOÀN (≥60%)
A24: → Đèn: GM có cao bất thường? | B24: =IF(B21>0.85,"NGHI NGỜ — nhiều khả năng bạn quên một khoản chi phí","OK") -> OK
A25: → Giá bán nằm trong vùng neo? | B25: =IF(AND(B19>=B7,B19<=MAX(B13,B16)),"OK — trong vùng giá bán","XEM LẠI — ngoài vùng giá sàn/trần") -> OK — trong vùng giá bán
A27: BREAKEVEN CONTAINMENT — ngưỡng sống còn
A28: Ký hiệu: v = chi phí biến đổi / job thử · q = QA / job thử · e = chi phí 1 ca escalate
A29: v — chi phí biến đổi / job thử | B29: ='1_Cost_Job'!B31+'1_Cost_Job'!B38+'1_Cost_Job'!B43+'1_Cost_Job'!B47 -> 0.045596
A30: q — QA nội bộ / job thử | B30: ='1_Cost_Job'!B51*('1_Cost_Job'!B52/60)*'1_Cost_Job'!B50 -> 0.015
A31: e — chi phí 1 ca escalate | B31: =IF('1_Cost_Job'!B6="B",('1_Cost_Job'!B53/60)*'1_Cost_Job'!B50,0) -> 0.9
A32: Gross Margin mục tiêu | B32: 0.6
A33: ★ Containment tối thiểu cần đạt | B33: =IF((B19*(1-B32)+B31)=0,0,(B29+B30+B31)/(B19*(1-B32)+B31)) -> 0.74120062 | D33: Công thức: R ≥ (v+q+e) / (P×(1−GM)+e)
A34: Containment hiện tại (từ tab 1) | B34: ='1_Cost_Job'!B10 -> 0.82
A35: → Kết luận | B35: =IF(B34>=B33,"ĐẠT — mô hình có lãi lành mạnh","CHƯA ĐẠT — phải tăng containment, tăng giá, hoặc đổi biến thể HITL") -> ĐẠT — mô hình có lãi lành mạnh
A37: SENSITIVITY — mô hình gãy ở đâu?
A38: Containment | B38: Cost/Job | C38: Gross Margin | D38: Đánh giá
A39: 0.5 | B39: =($B$29+$B$30+$B$31*(1-A39))/A39 -> 1.021192 | C39: =IF($B$19=0,0,1-B39/$B$19) -> -0.031507071 | D39: =IF(C39>=0.6,"An toàn",IF(C39>=0.5,"Cảnh báo","Nguy hiểm")) -> Nguy hiểm
A40: 0.6 | B40: =($B$29+$B$30+$B$31*(1-A40))/A40 -> 0.70099333 | C40: =IF($B$19=0,0,1-B40/$B$19) -> 0.29192593 | D40: =IF(C40>=0.6,"An toàn",IF(C40>=0.5,"Cảnh báo","Nguy hiểm")) -> Nguy hiểm
A41: 0.7 | B41: =($B$29+$B$30+$B$31*(1-A41))/A41 -> 0.47228 | C41: =IF($B$19=0,0,1-B41/$B$19) -> 0.52294949 | D41: =IF(C41>=0.6,"An toàn",IF(C41>=0.5,"Cảnh báo","Nguy hiểm")) -> Cảnh báo
A42: 0.8 | B42: =($B$29+$B$30+$B$31*(1-A42))/A42 -> 0.300745 | C42: =IF($B$19=0,0,1-B42/$B$19) -> 0.69621717 | D42: =IF(C42>=0.6,"An toàn",IF(C42>=0.5,"Cảnh báo","Nguy hiểm")) -> An toàn
A43: 0.9 | B43: =($B$29+$B$30+$B$31*(1-A43))/A43 -> 0.16732889 | C43: =IF($B$19=0,0,1-B43/$B$19) -> 0.83098092 | D43: =IF(C43>=0.6,"An toàn",IF(C43>=0.5,"Cảnh báo","Nguy hiểm")) -> An toàn
A44: 0.95 | B44: =($B$29+$B$30+$B$31*(1-A44))/A44 -> 0.11115368 | C44: =IF($B$19=0,0,1-B44/$B$19) -> 0.88772355 | D44: =IF(C44>=0.6,"An toàn",IF(C44>=0.5,"Cảnh báo","Nguy hiểm")) -> An toàn
A46: Nhìn cột Gross Margin: mô hình của bạn mong manh đến mức nào khi AI làm sai nhiều hơn dự kiến?
A48: 5 CON SỐ PHẢI MANG SANG ONE-PAGER
A49: Cost/Job | B49: =B5 -> 0.27145854
A50: Giá sàn (3×) | B50: =B7 -> 0.81437561
A51: Giá bán đề xuất | B51: =B19 -> 0.99
A52: Gross Margin | B52: =B21 -> 0.72579946
A53: Breakeven containment | B53: =B33 -> 0.74120062

Sheet 3_Value_Metric
A1: TAB 3 — VALUE METRIC SCORECARD
A2: Trạm 2. Chấm 0 / 1 / 2 điểm cho mỗi câu, theo THỰC TẾ HÔM NAY.
A4: A. ATTRIBUTION — bạn đo được kết quả là do AI tạo ra không?
A5: 1. Tôi có log đầy đủ mỗi job AI xử lý, gắn được với kết quả cuối cùng | B5: 2
A6: 2. Tôi có bộ eval đo được tỷ lệ AI làm đúng, có số liệu | B6: 2
A7: 3. Khách hàng đồng ý với cách tôi định nghĩa 'thành công' của một job | B7: 2
A8: 4. Tôi phân biệt được kết quả do AI tạo ra với kết quả do yếu tố khác | B8: 1
A9: 5. Tôi viết được định nghĩa chặt như Intercom: cái gì tính tiền, cái gì không | B9: 2
A10: → ĐIỂM ATTRIBUTION (tối đa 10) | B10: =SUM(B5:B9) -> 9
A12: B. AUTONOMY — AI tự chạy hay cần người?
A13: 1. AI hoàn thành job từ đầu đến cuối, không cần người bấm nút giữa chừng | B13: 1
A14: 2. Job chạy được ngoài giờ hành chính mà không ai trực | B14: 2
A15: 3. Khi AI không chắc, nó tự chuyển tiếp đúng chỗ — không cần người phân loại | B15: 2
A16: 4. Tỷ lệ ca phải có người can thiệp dưới 20% | B16: 1
A17: 5. Người vận hành chỉ kiểm tra mẫu (QA), không xử lý từng ca | B17: 1
A18: → ĐIỂM AUTONOMY (tối đa 10) | B18: =SUM(B13:B17) -> 7
A20: GỢI Ý CỦA MODEL
A21: → Value Metric gợi ý | B21: =IF(AND(B10>=7,B18>=7),"OUTCOME",IF(AND(B10>=7,B18<7),"USAGE",IF(AND(B10<7,B18>=7),"USAGE (an toàn)","SEAT hoặc HYBRID"))) -> OUTCOME
A22: Ngưỡng 7/10 là quy ước của bài tập, không phải chuẩn ngành — dùng để buộc bạn ra quyết định, không phải để thay bạn quyết định.
A24: BENCHMARK NGƯỢC — 2 sản phẩm thật cùng loại job
A25: Tên sản phẩm | B25: Value Metric | C25: Giá công bố | D25: Link nguồn
A26: Salesforce Agentforce | B26: Outcome / Action (Flex Credits) | C26: / conversation hoặc ,10 / action | D26: https://www.salesforce.com/agentforce/pricing/
A27: Intercom Fin | B27: Outcome (Resolution) | C27: ,99 / resolution thành công | D27: https://fin.ai/pricing/
A29: QUYẾT ĐỊNH CUỐI
A30: Value Metric tôi chọn | B30: Outcome
A31: Nếu KHÁC gợi ý — lý do thị trường là gì? | B31: Khớp hoàn toàn với gợi ý OUTCOME của model (Attribution 9/10, Autonomy 7/10); thị trường BĐS ưa chuộng trả theo kết quả hồ sơ báo giá bảo chứng thành công.
A32: Decision Note — câu 1: tôi chọn đơn vị nào? | B32: Tôi chọn đơn vị Outcome: ,99 / mỗi hồ sơ báo giá BĐS hợp lệ được phê duyệt chính thức (kèm snapshot SHA-256 bảo chứng).
A33: Decision Note — câu 2: bằng chứng Attribution / Autonomy? | B33: Attribution đạt 9/10 nhờ mã băm SHA-256, tọa độ chứng cứ Claim-Level F4 và bộ kiểm chuẩn 15 test cases kế toán chính xác 100%; Autonomy đạt 7/10 với containment 82% và cơ chế Safe Abstention tự động.
A34: Decision Note — câu 3: mô hình này lỗ trong tình huống nào? | B34: Mô hình này lỗ nếu tỷ lệ containment tụt dưới 74,1% (tỷ lệ ngoại lệ > 25,9%), khiến chi phí nhân sự xử lý ngoại lệ HITL tăng vọt nuốt chửng biên lợi nhuận; khắc phục bằng cách bổ sung phí nền tảng /tháng (hybrid) để bảo vệ giá sàn.

Sheet 4_Channel_Fit
A1: TAB 4 — CHANNEL FIT & AFFORDABILITY TEST
A2: Trạm 4. Chọn ĐÚNG 1 kênh cho 90 ngày đầu — và chứng minh bằng số.
A4: A. NGÂN SÁCH CAC — bạn nuôi nổi kênh nào?
A5: ARPU / tháng ($) | B5: 200
A6: Gross Margin (từ tab 2_Pricing) | B6: ='2_Pricing'!B21 -> 0.72579946
A7: Phân khúc (SMB / Mid / Enterprise) | B7: SMB
A8: → CAC payback cho phép (tháng) | B8: =IF(B7="SMB",12,IF(B7="Mid",18,24)) -> 12 | C8: tháng | D8: Bessemer, Scaling to $100M (2024)
A9: ★ NGÂN SÁCH CAC / khách | B9: =B5*B6*B8 -> 1741.9187 | D9: ARPU × GM × số tháng payback
A10: → ACV (giá trị hợp đồng / năm) | B10: =B5*12 -> 2400
A12: B. SALES VIABILITY — một AE phải chốt bao nhiêu deal?
A13: Quota / AE / năm ($) | B13: 500000 | D13: Giả định gốc của Tunguz (2016) — thay bằng số thị trường bạn
A14: Số ngày làm việc / năm | B14: 250 | C14: ngày
A15: → Số deal / AE / năm | B15: =IF(B10=0,0,B13/B10) -> 208.33333
A16: ★ Số deal / AE / NGÀY | B16: =IF(B14=0,0,B15/B14) -> 0.83333333 | C16: deal/ngày
A17: → Kết luận Sales-Led | B17: =IF(B16<=1,"KHẢ THI về mặt số học","BẤT KHẢ THI — ACV quá thấp để nuôi sales rep") -> KHẢ THI về mặt số học
A19: C. ĐỐI CHIẾU CAC THỰC TẾ CỦA MOTION CÓ SALES
A20: Cost per opportunity ($) | B20: 8000 | D20: ICONIQ 2026 theo phân khúc: $6.300 · $8.000 · $11.200
A21: Win rate | B21: 0.25
A22: → CAC thực tế ước tính / khách | B22: =IF(B21=0,0,B20/B21) -> 32000
A23: ★ Lệch bao nhiêu lần so với ngân sách CAC? | B23: =IF(B9=0,0,B22/B9) -> 18.370547 | D23: Đây là bằng chứng chọn kênh của bạn
A24: → Kết luận | B24: =IF(B23<=1,"Motion có sales KHẢ THI",IF(B23<=3,"Căng — cần tăng giá hoặc giảm chi phí bán hàng","KHÔNG KHẢ THI — đi PLG hoặc Partner-Led")) -> KHÔNG KHẢ THI — đi PLG hoặc Partner-Led
A26: D. CHẤM ĐIỂM 3 KÊNH (1 = rất kém, 5 = rất tốt)
A27: Tiêu chí | B27: PLG | C27: Sales-Led | D27: Partner-Led
A28: 1. Ngân sách CAC của tôi nuôi nổi kênh này | B28: 3 | C28: 1 | D28: 5
A29: 2. Khách hàng mục tiêu thực sự mua theo cách này | B29: 2 | C29: 4 | D29: 5
A30: 3. Đội hiện tại có năng lực chạy kênh này ngay | B30: 3 | C30: 3 | D30: 4
A31: 4. Tôi tiếp cận được điểm nhúng / partner trong 30 ngày | B31: 3 | C31: 3 | D31: 4
A32: 5. Kênh này đưa tôi đến ĐÚNG Pain Moment | B32: 3 | C32: 4 | D32: 5
A33: 6. Tôi đo được hiệu quả trong vòng 90 ngày | B33: 3 | C33: 3 | D33: 5
A34: → TỔNG ĐIỂM | B34: =SUM(B28:B33) -> 17 | C34: =SUM(C28:C33) -> 18 | D34: =SUM(D28:D33) -> 28
A35: → Kênh điểm cao nhất | B35: =IF(AND(B34>=C34,B34>=D34),"PLG",IF(C34>=D34,"Sales-Led","Partner-Led")) -> Partner-Led
A37: E. CHỐT KÊNH
A38: ★ Kênh tôi chọn cho 90 ngày đầu | B38: Partner-Led | D38: ĐÚNG 1 kênh. Chọn 2 kênh trở lên bị trừ điểm.
A39: Nếu Partner-Led: TÊN CÔNG TY partner | B39: Công ty Cổ phần Tập đoàn Meey Land (Nền tảng Meey CRM) | D39: 'Các nền tảng trong ngành' = chưa có kênh
A40: Đã nói chuyện với họ chưa? (Rồi / Chưa) | B40: Chưa
A41: Bạn mang lại giá trị gì cho partner? | B41: Tích hợp bộ công cụ tính giá chính sách tự động không ảo giác và đối soát chiết khấu bảo vệ biên lợi nhuận trực tiếp vào Meey CRM, giúp Meey CRM gia tăng giá trị cho hàng trăm sàn BĐS mà không cần tự phát triển AI.
A42: Nếu rơi vào vùng không khả thi — lối thoát nào? | B42: Đi Partner-Led: Cắm trực tiếp tính năng vào Meey CRM để tận dụng tệp hàng trăm sàn phân phối BĐS có sẵn, chia sẻ doanh thu (revenue share 20%), bypass hoàn toàn chi phí CAC direct sales. | D42: Giảm giá để tự phục vụ / tăng giá + service / Partner-Led

Sheet 5_90Day_Plan
A1: TAB 5 — PAIN MOMENT · 90-DAY PLAN · EVIDENCE PACK
A2: Trạm 5 và Trạm 6.
A4: A. PAIN MOMENT — phải đủ 3 phần
A5: MẤY GIỜ khách đau nhất? | B5: 20h30 tối (hoặc 10h15 sáng ngày mở bán sự kiện đông nghìn người)
A6: Lúc đó họ ĐANG LÀM GÌ? | B6: Khách hàng đòi chốt căn 4,5 tỷ nhưng yêu cầu cộng dồn voucher 100tr + chiết khấu thanh toán sớm 8% + ân hạn nợ gốc 24 tháng; nhân viên kinh doanh lúng túng mở 4 file Excel chính sách khác nhau (v2, v3, v3.1) không biết có vi phạm quy định hay bị trừ hoa hồng không, gọi Quản lý thì máy bận.
A7: Họ đang DÙNG APP / KÊNH NÀO? | B7: Nhóm chat Zalo trên điện thoại (đang gửi ảnh chụp màn hình bảng tính Excel và bảng giá niêm yết).
A8: → Điểm nhúng cụ thể của bạn | B8: Zalo Mini App & Web Extension nhúng trực tiếp trong màn hình quản lý giao dịch Meey CRM / VLandFuture Sales Portal. | D8: Một bề mặt tích hợp có tên, không phải 'website của chúng tôi'
A10: B. 90-DAY PLAN
B11: THÁNG 1 — Học | C11: THÁNG 2–3 — Đòn bẩy | D11: THÁNG 4+ — Mở rộng
A12: Kênh sử dụng | B12: Partner-Led (Pilot hẹp tại 1 sàn đối tác VLandFuture) | C12: Partner-Led (Mở rộng trong hệ sinh thái Meey CRM / VLandFuture) | D12: Partner-Led kết hợp Inbound Product-Led Expansion
A13: Mục tiêu số khách | B13: 1 sàn đối tác (40 sales tuyến đầu) | C13: 5 sàn phân phối BĐS (khoảng 200 sales) | D13: 20 sàn phân phối (khoảng 1.000 sales hoạt động)
A14: Việc cụ thể 1 | B14: Cài đặt Zalo Mini App cho 40 sales và số hóa 3 văn bản chính sách bán hàng hiện hành | C14: Tích hợp API chính thức vào Meey CRM để sales mở trực tiếp từ giỏ hàng | D14: Ra mắt gói tính năng nâng cao Multi-Project cho các Chủ đầu tư lớn
A15: Việc cụ thể 2 | B15: Product Lead trực tiếp túc trực tại sàn 3 buổi/tuần quan sát sales tư vấn thực tế | C15: Tổ chức 2 buổi workshop đào tạo trực tuyến cho 200 sales về cách dùng bảo chứng SHA-256 chốt cọc | D15: Triển khai chương trình chia sẻ doanh thu 20% với các đối tác phần mềm BĐS khác
A16: Việc cụ thể 3 | B16: Ghi nhận 100% ca Safe Abstention và lỗi tính toán để tinh chỉnh prompt + rule | C16: Thiết lập dashboard đối soát chiết khấu tự động cho Giám đốc sàn | D16: Tự động hóa hoàn toàn luồng onboarding dự án mới cho Policy Admin
A17: KPI đo được | B17: 300 báo giá được tạo, 0 lỗi sai số học, thời gian tạo báo giá < 15 giây | C17: 1.500 báo giá/tháng, tỷ lệ containment đạt ≥ 82%, NPS của sales đạt ≥ 60 | D17: 10.000 báo giá/tháng, MRR đạt .000, CAC Payback < 4 tháng
A18: Người chịu trách nhiệm | B18: Product Lead (Lead Product Strategist) | C18: Partnership Lead & Technical Solution Architect | D18: Head of Growth & CEO
A19: Tháng 1 là giai đoạn HỌC, không phải scale. Kế hoạch 'tháng 1 lấy 200 khách ở 5 ngành' là kế hoạch chưa ai từng thử làm.
A21: C. EVIDENCE PACK — 3 tài sản bán hàng
A22: Tài sản | B22: Đã có? (Rồi/Chưa) | C22: Nội dung 1 câu — hoặc việc cần làm | D22: Người phụ trách · Deadline
A23: 1. Eval Results | B23: Rồi | C23: Đạt 100% độ chính xác số học trên 15 Formula Regression test cases; tỷ lệ bắt xung đột chính sách đạt 99,5%; tỷ lệ dừng an toàn Safe Abstention đạt 100%. | D23: AI Tech Lead · Đã kiểm chuẩn 05/10/2026
A24: 2. Risk Checklist | B24: Rồi | C24: (1) Không ảo giác số học: 100% tính toán ủy thác cho Python Math Engine; (2) Data chính sách lưu trên Supabase pgvector nội bộ, không train public LLM; (3) Mọi báo giá lưu snapshot SHA-256 bất biến phục vụ kiểm toán độc lập 10 năm. | D24: Security & Compliance Lead · Hoàn tất 07/10/2026
A25: 3. Pilot Report | B25: Chưa | C25: Mục tiêu Pilot 4 tuần tại sàn VLandFuture: 1.200 lượt báo giá, thời gian duyệt giảm từ 2 giờ xuống 45 giây, 0 sai sót chiết khấu, ngăn chặn thất thoát tối thiểu 300 triệu VNĐ. | D25: Product Lead & Sàn VLandFuture · Deadline 30/11/2026
A26: Ô nào CHƯA CÓ thì ghi deadline — đừng bỏ trống. Thành thật về khoảng trống được điểm cao hơn bịa nội dung.
A28: D. BÀI TEST NGƯỜI LẠ — nhóm khác đọc One-Pager trong 2 phút
A29: Họ trả lời được: bán gì, cho ai, tính tiền theo đơn vị nào? (Được/Không) | B29: Được
A30: Họ trả lời được: có lãi trên mỗi đơn vị không, số nào chứng minh? (Được/Không) | B30: Được
A31: Họ trả lời được: tiếp cận khách qua đâu, vì sao kênh đó? (Được/Không) | B31: Được
A32: Số câu họ phải hỏi lại (mục tiêu ≤ 3) | B32: 1

Sheet 6_Benchmarks
A1: TAB 6 — BENCHMARKS (CHỈ ĐỌC)
A2: Giá chốt ngày 26/08/2026. Dòng có ⏳ là GIÁ KHUYẾN MẠI CÓ HẠN — phải kiểm tra lại.
A3: NGÀY BẠN KIỂM TRA LẠI GIÁ | B3: 08/10/2026 | D3: Bắt buộc điền — Rubric có chấm mục này
A5: Nhóm | B5: Mục | C5: Giá | D5: Đơn vị | E5: Nguồn
A6: LLM | B6: Claude Opus 5 — input / output | C6: 5,00 / 25,00 | D6: $ / 1M token | E6: platform.claude.com/docs/en/about-claude/pricing
A7: LLM | B7: Claude Sonnet 5 — input / output | C7: 2,00 / 10,00 | D7: $ / 1M token | E7: platform.claude.com/docs/en/about-claude/pricing
A8: LLM | B8: Claude Haiku 4.5 — input / output | C8: 1,00 / 5,00 | D8: $ / 1M token | E8: platform.claude.com/docs/en/about-claude/pricing
A9: LLM | B9: Claude — cache write 5' / cache read | C9: 1,25× / 0,10× input | D9: hệ số | E9: platform.claude.com/docs/en/about-claude/pricing
A10: LLM | B10: ⏳ OpenAI GPT-5.6 Sol — input / output | C10: 4,00 / 20,00 | D10: $ / 1M token | E10: developers.openai.com/api/docs/pricing (KM 21/08–21/11/2026; list 5,00/30,00)
A11: LLM | B11: OpenAI GPT-5.6 Luna — input / output | C11: 0,20 / 1,20 | D11: $ / 1M token | E11: developers.openai.com/api/docs/pricing
A12: LLM | B12: OpenAI — cached input / Batch API | C12: 10% input / −50% | D12: hệ số | E12: developers.openai.com/api/docs/pricing
A13: LLM | B13: Gemini 3.1 Pro — input / output (≤200k) | C13: 2,00 / 12,00 | D13: $ / 1M token | E13: ai.google.dev/gemini-api/docs/pricing
A14: LLM | B14: ⏳ Gemini 3.7 Flash — input / output | C14: 0,75 / 3,75 | D14: $ / 1M token | E14: ai.google.dev/gemini-api/docs/pricing (KM đến 31/12/2026; sau đó 1,50/7,50)
A15: STT | B15: Deepgram Nova-3 — pre-recorded | C15: 0,0043 | D15: $ / phút | E15: deepgram.com/pricing
A16: STT | B16: ⏳ Deepgram Nova-3 — streaming | C16: list 0,0077 · KM 0,0048 | D16: $ / phút | E16: deepgram.com/pricing — đang khuyến mại, kiểm tra lại
... A41: Benchmark | B41: ACV sàn cho inside sales | C41: ≈ 3.000 | D41: $ / năm | E41: Tomasz Tunguz (2016) — có kèm giả định để tính lại
